Compiled from "LivingEntityRenderer.java"
public abstract class net.minecraft.client.render.entity.LivingEntityRenderer<T extends net.minecraft.entity.LivingEntity, S extends net.minecraft.client.render.entity.state.LivingEntityRenderState, M extends net.minecraft.client.render.entity.model.EntityModel<? super S>> extends net.minecraft.client.render.entity.EntityRenderer<T, S> implements net.minecraft.client.render.entity.feature.FeatureRendererContext<S, M> {
  private static final float field_32939;
    descriptor: F

  protected M model;
    descriptor: Lnet/minecraft/client/render/entity/model/EntityModel;

  protected final net.minecraft.client.item.ItemModelManager itemModelResolver;
    descriptor: Lnet/minecraft/client/item/ItemModelManager;

  protected final java.util.List<net.minecraft.client.render.entity.feature.FeatureRenderer<S, M>> features;
    descriptor: Ljava/util/List;

  public net.minecraft.client.render.entity.LivingEntityRenderer(net.minecraft.client.render.entity.EntityRendererFactory$Context, M, float);
    descriptor: (Lnet/minecraft/client/render/entity/EntityRendererFactory$Context;Lnet/minecraft/client/render/entity/model/EntityModel;F)V
    Code:
       0: aload_0
       1: aload_1
       2: invokespecial #48                 // Method net/minecraft/client/render/entity/EntityRenderer."<init>":(Lnet/minecraft/client/render/entity/EntityRendererFactory$Context;)V
       5: aload_0
       6: invokestatic  #54                 // Method com/google/common/collect/Lists.newArrayList:()Ljava/util/ArrayList;
       9: putfield      #56                 // Field features:Ljava/util/List;
      12: aload_0
      13: aload_1
      14: invokevirtual #60                 // Method net/minecraft/client/render/entity/EntityRendererFactory$Context.getItemModelManager:()Lnet/minecraft/client/item/ItemModelManager;
      17: putfield      #62                 // Field itemModelResolver:Lnet/minecraft/client/item/ItemModelManager;
      20: aload_0
      21: aload_2
      22: putfield      #64                 // Field model:Lnet/minecraft/client/render/entity/model/EntityModel;
      25: aload_0
      26: fload_3
      27: putfield      #66                 // Field shadowRadius:F
      30: return

  protected final boolean addFeature(net.minecraft.client.render.entity.feature.FeatureRenderer<S, M>);
    descriptor: (Lnet/minecraft/client/render/entity/feature/FeatureRenderer;)Z
    Code:
       0: aload_0
       1: getfield      #56                 // Field features:Ljava/util/List;
       4: aload_1
       5: invokeinterface #80,  2           // InterfaceMethod java/util/List.add:(Ljava/lang/Object;)Z
      10: ireturn

  public M getModel();
    descriptor: ()Lnet/minecraft/client/render/entity/model/EntityModel;
    Code:
       0: aload_0
       1: getfield      #64                 // Field model:Lnet/minecraft/client/render/entity/model/EntityModel;
       4: areturn

  protected net.minecraft.util.math.Box getBoundingBox(T);
    descriptor: (Lnet/minecraft/entity/LivingEntity;)Lnet/minecraft/util/math/Box;
    Code:
       0: aload_0
       1: aload_1
       2: invokespecial #92                 // Method net/minecraft/client/render/entity/EntityRenderer.getBoundingBox:(Lnet/minecraft/entity/Entity;)Lnet/minecraft/util/math/Box;
       5: astore_2
       6: aload_1
       7: getstatic     #98                 // Field net/minecraft/entity/EquipmentSlot.HEAD:Lnet/minecraft/entity/EquipmentSlot;
      10: invokevirtual #104                // Method net/minecraft/entity/LivingEntity.getEquippedStack:(Lnet/minecraft/entity/EquipmentSlot;)Lnet/minecraft/item/ItemStack;
      13: getstatic     #110                // Field net/minecraft/item/Items.DRAGON_HEAD:Lnet/minecraft/item/Item;
      16: invokevirtual #116                // Method net/minecraft/item/ItemStack.isOf:(Lnet/minecraft/item/Item;)Z
      19: ifeq          39
      22: ldc           #117                // float 0.5f
      24: fstore_3
      25: aload_2
      26: ldc2_w        #118                // double 0.5d
      29: ldc2_w        #118                // double 0.5d
      32: ldc2_w        #118                // double 0.5d
      35: invokevirtual #125                // Method net/minecraft/util/math/Box.expand:(DDD)Lnet/minecraft/util/math/Box;
      38: areturn
      39: aload_2
      40: areturn

  public void render(S, net.minecraft.client.util.math.MatrixStack, net.minecraft.client.render.VertexConsumerProvider, int);
    descriptor: (Lnet/minecraft/client/render/entity/state/LivingEntityRenderState;Lnet/minecraft/client/util/math/MatrixStack;Lnet/minecraft/client/render/VertexConsumerProvider;I)V
    Code:
       0: aload_2
       1: invokevirtual #143                // Method net/minecraft/client/util/math/MatrixStack.push:()V
       4: aload_1
       5: getstatic     #149                // Field net/minecraft/entity/EntityPose.SLEEPING:Lnet/minecraft/entity/EntityPose;
       8: invokevirtual #155                // Method net/minecraft/client/render/entity/state/LivingEntityRenderState.isInPose:(Lnet/minecraft/entity/EntityPose;)Z
      11: ifeq          59
      14: aload_1
      15: getfield      #159                // Field net/minecraft/client/render/entity/state/LivingEntityRenderState.sleepingDirection:Lnet/minecraft/util/math/Direction;
      18: astore        5
      20: aload         5
      22: ifnull        59
      25: aload_1
      26: getfield      #162                // Field net/minecraft/client/render/entity/state/LivingEntityRenderState.standingEyeHeight:F
      29: ldc           #32                 // float 0.1f
      31: fsub
      32: fstore        6
      34: aload_2
      35: aload         5
      37: invokevirtual #168                // Method net/minecraft/util/math/Direction.getOffsetX:()I
      40: ineg
      41: i2f
      42: fload         6
      44: fmul
      45: fconst_0
      46: aload         5
      48: invokevirtual #171                // Method net/minecraft/util/math/Direction.getOffsetZ:()I
      51: ineg
      52: i2f
      53: fload         6
      55: fmul
      56: invokevirtual #175                // Method net/minecraft/client/util/math/MatrixStack.translate:(FFF)V
      59: aload_1
      60: getfield      #178                // Field net/minecraft/client/render/entity/state/LivingEntityRenderState.baseScale:F
      63: fstore        5
      65: aload_2
      66: fload         5
      68: fload         5
      70: fload         5
      72: invokevirtual #181                // Method net/minecraft/client/util/math/MatrixStack.scale:(FFF)V
      75: aload_0
      76: aload_1
      77: aload_2
      78: aload_1
      79: getfield      #184                // Field net/minecraft/client/render/entity/state/LivingEntityRenderState.bodyYaw:F
      82: fload         5
      84: invokevirtual #188                // Method setupTransforms:(Lnet/minecraft/client/render/entity/state/LivingEntityRenderState;Lnet/minecraft/client/util/math/MatrixStack;FF)V
      87: aload_2
      88: ldc           #189                // float -1.0f
      90: ldc           #189                // float -1.0f
      92: fconst_1
      93: invokevirtual #181                // Method net/minecraft/client/util/math/MatrixStack.scale:(FFF)V
      96: aload_0
      97: aload_1
      98: aload_2
      99: invokevirtual #192                // Method scale:(Lnet/minecraft/client/render/entity/state/LivingEntityRenderState;Lnet/minecraft/client/util/math/MatrixStack;)V
     102: aload_2
     103: fconst_0
     104: ldc           #193                // float -1.501f
     106: fconst_0
     107: invokevirtual #175                // Method net/minecraft/client/util/math/MatrixStack.translate:(FFF)V
     110: aload_0
     111: getfield      #64                 // Field model:Lnet/minecraft/client/render/entity/model/EntityModel;
     114: aload_1
     115: invokevirtual #199                // Method net/minecraft/client/render/entity/model/EntityModel.setAngles:(Lnet/minecraft/client/render/entity/state/EntityRenderState;)V
     118: aload_0
     119: aload_1
     120: invokevirtual #203                // Method isVisible:(Lnet/minecraft/client/render/entity/state/LivingEntityRenderState;)Z
     123: istore        6
     125: iload         6
     127: ifne          141
     130: aload_1
     131: getfield      #207                // Field net/minecraft/client/render/entity/state/LivingEntityRenderState.invisibleToPlayer:Z
     134: ifne          141
     137: iconst_1
     138: goto          142
     141: iconst_0
     142: istore        7
     144: aload_0
     145: aload_1
     146: iload         6
     148: iload         7
     150: aload_1
     151: getfield      #210                // Field net/minecraft/client/render/entity/state/LivingEntityRenderState.hasOutline:Z
     154: invokevirtual #214                // Method getRenderLayer:(Lnet/minecraft/client/render/entity/state/LivingEntityRenderState;ZZZ)Lnet/minecraft/client/render/RenderLayer;
     157: astore        8
     159: aload         8
     161: ifnull        226
     164: aload_3
     165: aload         8
     167: invokeinterface #220,  2          // InterfaceMethod net/minecraft/client/render/VertexConsumerProvider.getBuffer:(Lnet/minecraft/client/render/RenderLayer;)Lnet/minecraft/client/render/VertexConsumer;
     172: astore        9
     174: aload_1
     175: aload_0
     176: aload_1
     177: invokevirtual #224                // Method getAnimationCounter:(Lnet/minecraft/client/render/entity/state/LivingEntityRenderState;)F
     180: invokestatic  #228                // Method getOverlay:(Lnet/minecraft/client/render/entity/state/LivingEntityRenderState;F)I
     183: istore        10
     185: iload         7
     187: ifeq          195
     190: ldc           #229                // int 654311423
     192: goto          196
     195: iconst_m1
     196: istore        11
     198: iload         11
     200: aload_0
     201: aload_1
     202: invokevirtual #235                // Method getMixColor:(Lnet/minecraft/client/render/entity/state/LivingEntityRenderState;)I
     205: invokestatic  #241                // Method net/minecraft/util/math/ColorHelper.mix:(II)I
     208: istore        12
     210: aload_0
     211: getfield      #64                 // Field model:Lnet/minecraft/client/render/entity/model/EntityModel;
     214: aload_2
     215: aload         9
     217: iload         4
     219: iload         10
     221: iload         12
     223: invokevirtual #244                // Method net/minecraft/client/render/entity/model/EntityModel.render:(Lnet/minecraft/client/util/math/MatrixStack;Lnet/minecraft/client/render/VertexConsumer;III)V
     226: aload_0
     227: aload_1
     228: invokevirtual #247                // Method shouldRenderFeatures:(Lnet/minecraft/client/render/entity/state/LivingEntityRenderState;)Z
     231: ifeq          288
     234: aload_0
     235: getfield      #56                 // Field features:Ljava/util/List;
     238: invokeinterface #251,  1          // InterfaceMethod java/util/List.iterator:()Ljava/util/Iterator;
     243: astore        9
     245: aload         9
     247: invokeinterface #257,  1          // InterfaceMethod java/util/Iterator.hasNext:()Z
     252: ifeq          288
     255: aload         9
     257: invokeinterface #261,  1          // InterfaceMethod java/util/Iterator.next:()Ljava/lang/Object;
     262: checkcast     #263                // class net/minecraft/client/render/entity/feature/FeatureRenderer
     265: astore        10
     267: aload         10
     269: aload_2
     270: aload_3
     271: iload         4
     273: aload_1
     274: aload_1
     275: getfield      #266                // Field net/minecraft/client/render/entity/state/LivingEntityRenderState.yawDegrees:F
     278: aload_1
     279: getfield      #269                // Field net/minecraft/client/render/entity/state/LivingEntityRenderState.pitch:F
     282: invokevirtual #272                // Method net/minecraft/client/render/entity/feature/FeatureRenderer.render:(Lnet/minecraft/client/util/math/MatrixStack;Lnet/minecraft/client/render/VertexConsumerProvider;ILnet/minecraft/client/render/entity/state/EntityRenderState;FF)V
     285: goto          245
     288: aload_2
     289: invokevirtual #275                // Method net/minecraft/client/util/math/MatrixStack.pop:()V
     292: aload_0
     293: aload_1
     294: aload_2
     295: aload_3
     296: iload         4
     298: invokespecial #278                // Method net/minecraft/client/render/entity/EntityRenderer.render:(Lnet/minecraft/client/render/entity/state/EntityRenderState;Lnet/minecraft/client/util/math/MatrixStack;Lnet/minecraft/client/render/VertexConsumerProvider;I)V
     301: return

  protected boolean shouldRenderFeatures(S);
    descriptor: (Lnet/minecraft/client/render/entity/state/LivingEntityRenderState;)Z
    Code:
       0: iconst_1
       1: ireturn

  protected int getMixColor(S);
    descriptor: (Lnet/minecraft/client/render/entity/state/LivingEntityRenderState;)I
    Code:
       0: iconst_m1
       1: ireturn

  public abstract net.minecraft.util.Identifier getTexture(S);
    descriptor: (Lnet/minecraft/client/render/entity/state/LivingEntityRenderState;)Lnet/minecraft/util/Identifier;

  protected net.minecraft.client.render.RenderLayer getRenderLayer(S, boolean, boolean, boolean);
    descriptor: (Lnet/minecraft/client/render/entity/state/LivingEntityRenderState;ZZZ)Lnet/minecraft/client/render/RenderLayer;
    Code:
       0: aload_0
       1: aload_1
       2: invokevirtual #308                // Method getTexture:(Lnet/minecraft/client/render/entity/state/LivingEntityRenderState;)Lnet/minecraft/util/Identifier;
       5: astore        5
       7: iload_3
       8: ifeq          17
      11: aload         5
      13: invokestatic  #314                // Method net/minecraft/client/render/RenderLayer.getItemEntityTranslucentCull:(Lnet/minecraft/util/Identifier;)Lnet/minecraft/client/render/RenderLayer;
      16: areturn
      17: iload_2
      18: ifeq          31
      21: aload_0
      22: getfield      #64                 // Field model:Lnet/minecraft/client/render/entity/model/EntityModel;
      25: aload         5
      27: invokevirtual #319                // Method net/minecraft/client/render/entity/model/EntityModel.getLayer:(Lnet/minecraft/util/Identifier;)Lnet/minecraft/client/render/RenderLayer;
      30: areturn
      31: iload         4
      33: ifeq          42
      36: aload         5
      38: invokestatic  #322                // Method net/minecraft/client/render/RenderLayer.getOutline:(Lnet/minecraft/util/Identifier;)Lnet/minecraft/client/render/RenderLayer;
      41: areturn
      42: aconst_null
      43: areturn

  public static int getOverlay(net.minecraft.client.render.entity.state.LivingEntityRenderState, float);
    descriptor: (Lnet/minecraft/client/render/entity/state/LivingEntityRenderState;F)I
    Code:
       0: fload_1
       1: invokestatic  #331                // Method net/minecraft/client/render/OverlayTexture.getU:(F)I
       4: aload_0
       5: getfield      #334                // Field net/minecraft/client/render/entity/state/LivingEntityRenderState.hurt:Z
       8: invokestatic  #338                // Method net/minecraft/client/render/OverlayTexture.getV:(Z)I
      11: invokestatic  #341                // Method net/minecraft/client/render/OverlayTexture.packUv:(II)I
      14: ireturn

  protected boolean isVisible(S);
    descriptor: (Lnet/minecraft/client/render/entity/state/LivingEntityRenderState;)Z
    Code:
       0: aload_1
       1: getfield      #344                // Field net/minecraft/client/render/entity/state/LivingEntityRenderState.invisible:Z
       4: ifne          11
       7: iconst_1
       8: goto          12
      11: iconst_0
      12: ireturn

  private static float getYaw(net.minecraft.util.math.Direction);
    descriptor: (Lnet/minecraft/util/math/Direction;)F
    Code:
       0: getstatic     #350                // Field net/minecraft/client/render/entity/LivingEntityRenderer$1.field_18227:[I
       3: aload_0
       4: invokevirtual #353                // Method net/minecraft/util/math/Direction.ordinal:()I
       7: iaload
       8: tableswitch   { // 1 to 4
                     1: 40
                     2: 44
                     3: 46
                     4: 50
               default: 54
          }
      40: ldc_w         #354                // float 90.0f
      43: freturn
      44: fconst_0
      45: freturn
      46: ldc_w         #355                // float 270.0f
      49: freturn
      50: ldc_w         #356                // float 180.0f
      53: freturn
      54: fconst_0
      55: freturn

  protected boolean isShaking(S);
    descriptor: (Lnet/minecraft/client/render/entity/state/LivingEntityRenderState;)Z
    Code:
       0: aload_1
       1: getfield      #360                // Field net/minecraft/client/render/entity/state/LivingEntityRenderState.shaking:Z
       4: ireturn

  protected void setupTransforms(S, net.minecraft.client.util.math.MatrixStack, float, float);
    descriptor: (Lnet/minecraft/client/render/entity/state/LivingEntityRenderState;Lnet/minecraft/client/util/math/MatrixStack;FF)V
    Code:
       0: aload_0
       1: aload_1
       2: invokevirtual #365                // Method isShaking:(Lnet/minecraft/client/render/entity/state/LivingEntityRenderState;)Z
       5: ifeq          36
       8: fload_3
       9: aload_1
      10: getfield      #368                // Field net/minecraft/client/render/entity/state/LivingEntityRenderState.age:F
      13: invokestatic  #373                // Method net/minecraft/util/math/MathHelper.floor:(F)I
      16: i2f
      17: ldc_w         #374                // float 3.25f
      20: fmul
      21: f2d
      22: invokestatic  #380                // Method java/lang/Math.cos:(D)D
      25: ldc2_w        #381                // double 3.141592653589793d
      28: dmul
      29: ldc2_w        #383                // double 0.4000000059604645d
      32: dmul
      33: d2f
      34: fadd
      35: fstore_3
      36: aload_1
      37: getstatic     #149                // Field net/minecraft/entity/EntityPose.SLEEPING:Lnet/minecraft/entity/EntityPose;
      40: invokevirtual #155                // Method net/minecraft/client/render/entity/state/LivingEntityRenderState.isInPose:(Lnet/minecraft/entity/EntityPose;)Z
      43: ifne          63
      46: aload_2
      47: getstatic     #390                // Field net/minecraft/util/math/RotationAxis.POSITIVE_Y:Lnet/minecraft/util/math/RotationAxis;
      50: ldc_w         #356                // float 180.0f
      53: fload_3
      54: fsub
      55: invokeinterface #394,  2          // InterfaceMethod net/minecraft/util/math/RotationAxis.rotationDegrees:(F)Lorg/joml/Quaternionf;
      60: invokevirtual #398                // Method net/minecraft/client/util/math/MatrixStack.multiply:(Lorg/joml/Quaternionf;)V
      63: aload_1
      64: getfield      #401                // Field net/minecraft/client/render/entity/state/LivingEntityRenderState.deathTime:F
      67: fconst_0
      68: fcmpl
      69: ifle          127
      72: aload_1
      73: getfield      #401                // Field net/minecraft/client/render/entity/state/LivingEntityRenderState.deathTime:F
      76: fconst_1
      77: fsub
      78: ldc_w         #402                // float 20.0f
      81: fdiv
      82: ldc_w         #403                // float 1.6f
      85: fmul
      86: fstore        5
      88: fload         5
      90: invokestatic  #407                // Method net/minecraft/util/math/MathHelper.sqrt:(F)F
      93: fstore        5
      95: fload         5
      97: fconst_1
      98: fcmpl
      99: ifle          105
     102: fconst_1
     103: fstore        5
     105: aload_2
     106: getstatic     #410                // Field net/minecraft/util/math/RotationAxis.POSITIVE_Z:Lnet/minecraft/util/math/RotationAxis;
     109: fload         5
     111: aload_0
     112: invokevirtual #414                // Method method_3919:()F
     115: fmul
     116: invokeinterface #394,  2          // InterfaceMethod net/minecraft/util/math/RotationAxis.rotationDegrees:(F)Lorg/joml/Quaternionf;
     121: invokevirtual #398                // Method net/minecraft/client/util/math/MatrixStack.multiply:(Lorg/joml/Quaternionf;)V
     124: goto          295
     127: aload_1
     128: getfield      #417                // Field net/minecraft/client/render/entity/state/LivingEntityRenderState.usingRiptide:Z
     131: ifeq          177
     134: aload_2
     135: getstatic     #420                // Field net/minecraft/util/math/RotationAxis.POSITIVE_X:Lnet/minecraft/util/math/RotationAxis;
     138: ldc_w         #421                // float -90.0f
     141: aload_1
     142: getfield      #269                // Field net/minecraft/client/render/entity/state/LivingEntityRenderState.pitch:F
     145: fsub
     146: invokeinterface #394,  2          // InterfaceMethod net/minecraft/util/math/RotationAxis.rotationDegrees:(F)Lorg/joml/Quaternionf;
     151: invokevirtual #398                // Method net/minecraft/client/util/math/MatrixStack.multiply:(Lorg/joml/Quaternionf;)V
     154: aload_2
     155: getstatic     #390                // Field net/minecraft/util/math/RotationAxis.POSITIVE_Y:Lnet/minecraft/util/math/RotationAxis;
     158: aload_1
     159: getfield      #368                // Field net/minecraft/client/render/entity/state/LivingEntityRenderState.age:F
     162: ldc_w         #422                // float -75.0f
     165: fmul
     166: invokeinterface #394,  2          // InterfaceMethod net/minecraft/util/math/RotationAxis.rotationDegrees:(F)Lorg/joml/Quaternionf;
     171: invokevirtual #398                // Method net/minecraft/client/util/math/MatrixStack.multiply:(Lorg/joml/Quaternionf;)V
     174: goto          295
     177: aload_1
     178: getstatic     #149                // Field net/minecraft/entity/EntityPose.SLEEPING:Lnet/minecraft/entity/EntityPose;
     181: invokevirtual #155                // Method net/minecraft/client/render/entity/state/LivingEntityRenderState.isInPose:(Lnet/minecraft/entity/EntityPose;)Z
     184: ifeq          257
     187: aload_1
     188: getfield      #159                // Field net/minecraft/client/render/entity/state/LivingEntityRenderState.sleepingDirection:Lnet/minecraft/util/math/Direction;
     191: astore        5
     193: aload         5
     195: ifnull        206
     198: aload         5
     200: invokestatic  #424                // Method getYaw:(Lnet/minecraft/util/math/Direction;)F
     203: goto          207
     206: fload_3
     207: fstore        6
     209: aload_2
     210: getstatic     #390                // Field net/minecraft/util/math/RotationAxis.POSITIVE_Y:Lnet/minecraft/util/math/RotationAxis;
     213: fload         6
     215: invokeinterface #394,  2          // InterfaceMethod net/minecraft/util/math/RotationAxis.rotationDegrees:(F)Lorg/joml/Quaternionf;
     220: invokevirtual #398                // Method net/minecraft/client/util/math/MatrixStack.multiply:(Lorg/joml/Quaternionf;)V
     223: aload_2
     224: getstatic     #410                // Field net/minecraft/util/math/RotationAxis.POSITIVE_Z:Lnet/minecraft/util/math/RotationAxis;
     227: aload_0
     228: invokevirtual #414                // Method method_3919:()F
     231: invokeinterface #394,  2          // InterfaceMethod net/minecraft/util/math/RotationAxis.rotationDegrees:(F)Lorg/joml/Quaternionf;
     236: invokevirtual #398                // Method net/minecraft/client/util/math/MatrixStack.multiply:(Lorg/joml/Quaternionf;)V
     239: aload_2
     240: getstatic     #390                // Field net/minecraft/util/math/RotationAxis.POSITIVE_Y:Lnet/minecraft/util/math/RotationAxis;
     243: ldc_w         #355                // float 270.0f
     246: invokeinterface #394,  2          // InterfaceMethod net/minecraft/util/math/RotationAxis.rotationDegrees:(F)Lorg/joml/Quaternionf;
     251: invokevirtual #398                // Method net/minecraft/client/util/math/MatrixStack.multiply:(Lorg/joml/Quaternionf;)V
     254: goto          295
     257: aload_1
     258: getfield      #427                // Field net/minecraft/client/render/entity/state/LivingEntityRenderState.flipUpsideDown:Z
     261: ifeq          295
     264: aload_2
     265: fconst_0
     266: aload_1
     267: getfield      #430                // Field net/minecraft/client/render/entity/state/LivingEntityRenderState.height:F
     270: ldc           #32                 // float 0.1f
     272: fadd
     273: fload         4
     275: fdiv
     276: fconst_0
     277: invokevirtual #175                // Method net/minecraft/client/util/math/MatrixStack.translate:(FFF)V
     280: aload_2
     281: getstatic     #410                // Field net/minecraft/util/math/RotationAxis.POSITIVE_Z:Lnet/minecraft/util/math/RotationAxis;
     284: ldc_w         #356                // float 180.0f
     287: invokeinterface #394,  2          // InterfaceMethod net/minecraft/util/math/RotationAxis.rotationDegrees:(F)Lorg/joml/Quaternionf;
     292: invokevirtual #398                // Method net/minecraft/client/util/math/MatrixStack.multiply:(Lorg/joml/Quaternionf;)V
     295: return

  protected float method_3919();
    descriptor: ()F
    Code:
       0: ldc_w         #354                // float 90.0f
       3: freturn

  protected float getAnimationCounter(S);
    descriptor: (Lnet/minecraft/client/render/entity/state/LivingEntityRenderState;)F
    Code:
       0: fconst_0
       1: freturn

  protected void scale(S, net.minecraft.client.util.math.MatrixStack);
    descriptor: (Lnet/minecraft/client/render/entity/state/LivingEntityRenderState;Lnet/minecraft/client/util/math/MatrixStack;)V
    Code:
       0: return

  protected boolean hasLabel(T, double);
    descriptor: (Lnet/minecraft/entity/LivingEntity;D)Z
    Code:
       0: aload_1
       1: invokevirtual #439                // Method net/minecraft/entity/LivingEntity.isSneaky:()Z
       4: ifeq          22
       7: ldc_w         #440                // float 32.0f
      10: fstore        4
      12: dload_2
      13: ldc2_w        #441                // double 1024.0d
      16: dcmpl
      17: iflt          22
      20: iconst_0
      21: ireturn
      22: invokestatic  #448                // Method net/minecraft/client/MinecraftClient.getInstance:()Lnet/minecraft/client/MinecraftClient;
      25: astore        4
      27: aload         4
      29: getfield      #452                // Field net/minecraft/client/MinecraftClient.player:Lnet/minecraft/client/network/ClientPlayerEntity;
      32: astore        5
      34: aload_1
      35: aload         5
      37: invokevirtual #456                // Method net/minecraft/entity/LivingEntity.isInvisibleTo:(Lnet/minecraft/entity/player/PlayerEntity;)Z
      40: ifne          47
      43: iconst_1
      44: goto          48
      47: iconst_0
      48: istore        6
      50: aload_1
      51: aload         5
      53: if_acmpeq     197
      56: aload_1
      57: invokevirtual #462                // Method net/minecraft/entity/LivingEntity.getScoreboardTeam:()Lnet/minecraft/scoreboard/Team;
      60: astore        7
      62: aload         5
      64: invokevirtual #463                // Method net/minecraft/client/network/ClientPlayerEntity.getScoreboardTeam:()Lnet/minecraft/scoreboard/Team;
      67: astore        8
      69: aload         7
      71: ifnull        197
      74: aload         7
      76: invokevirtual #467                // Method net/minecraft/scoreboard/AbstractTeam.getNameTagVisibilityRule:()Lnet/minecraft/scoreboard/AbstractTeam$VisibilityRule;
      79: astore        9
      81: getstatic     #470                // Field net/minecraft/client/render/entity/LivingEntityRenderer$1.field_4743:[I
      84: aload         9
      86: invokevirtual #471                // Method net/minecraft/scoreboard/AbstractTeam$VisibilityRule.ordinal:()I
      89: iaload
      90: tableswitch   { // 1 to 4
                     1: 120
                     2: 123
                     3: 125
                     4: 164
               default: 195
          }
     120: iload         6
     122: ireturn
     123: iconst_0
     124: ireturn
     125: aload         8
     127: ifnonnull     135
     130: iload         6
     132: goto          163
     135: aload         7
     137: aload         8
     139: invokevirtual #477                // Method net/minecraft/scoreboard/AbstractTeam.isEqual:(Lnet/minecraft/scoreboard/AbstractTeam;)Z
     142: ifeq          162
     145: aload         7
     147: invokevirtual #480                // Method net/minecraft/scoreboard/AbstractTeam.shouldShowFriendlyInvisibles:()Z
     150: ifne          158
     153: iload         6
     155: ifeq          162
     158: iconst_1
     159: goto          163
     162: iconst_0
     163: ireturn
     164: aload         8
     166: ifnonnull     174
     169: iload         6
     171: goto          194
     174: aload         7
     176: aload         8
     178: invokevirtual #477                // Method net/minecraft/scoreboard/AbstractTeam.isEqual:(Lnet/minecraft/scoreboard/AbstractTeam;)Z
     181: ifne          193
     184: iload         6
     186: ifeq          193
     189: iconst_1
     190: goto          194
     193: iconst_0
     194: ireturn
     195: iconst_1
     196: ireturn
     197: invokestatic  #483                // Method net/minecraft/client/MinecraftClient.isHudEnabled:()Z
     200: ifeq          228
     203: aload_1
     204: aload         4
     206: invokevirtual #487                // Method net/minecraft/client/MinecraftClient.getCameraEntity:()Lnet/minecraft/entity/Entity;
     209: if_acmpeq     228
     212: iload         6
     214: ifeq          228
     217: aload_1
     218: invokevirtual #490                // Method net/minecraft/entity/LivingEntity.hasPassengers:()Z
     221: ifne          228
     224: iconst_1
     225: goto          229
     228: iconst_0
     229: ireturn

  public static boolean shouldFlipUpsideDown(net.minecraft.entity.LivingEntity);
    descriptor: (Lnet/minecraft/entity/LivingEntity;)Z
    Code:
       0: aload_0
       1: instanceof    #504                // class net/minecraft/entity/player/PlayerEntity
       4: ifne          14
       7: aload_0
       8: invokevirtual #507                // Method net/minecraft/entity/LivingEntity.hasCustomName:()Z
      11: ifeq          73
      14: aload_0
      15: invokevirtual #511                // Method net/minecraft/entity/LivingEntity.getName:()Lnet/minecraft/text/Text;
      18: invokeinterface #517,  1          // InterfaceMethod net/minecraft/text/Text.getString:()Ljava/lang/String;
      23: invokestatic  #523                // Method net/minecraft/util/Formatting.strip:(Ljava/lang/String;)Ljava/lang/String;
      26: astore_1
      27: ldc_w         #525                // String Dinnerbone
      30: aload_1
      31: invokevirtual #530                // Method java/lang/String.equals:(Ljava/lang/Object;)Z
      34: ifne          47
      37: ldc_w         #532                // String Grumm
      40: aload_1
      41: invokevirtual #530                // Method java/lang/String.equals:(Ljava/lang/Object;)Z
      44: ifeq          73
      47: aload_0
      48: instanceof    #504                // class net/minecraft/entity/player/PlayerEntity
      51: ifeq          67
      54: aload_0
      55: checkcast     #504                // class net/minecraft/entity/player/PlayerEntity
      58: getstatic     #538                // Field net/minecraft/entity/player/PlayerModelPart.CAPE:Lnet/minecraft/entity/player/PlayerModelPart;
      61: invokevirtual #542                // Method net/minecraft/entity/player/PlayerEntity.isPartVisible:(Lnet/minecraft/entity/player/PlayerModelPart;)Z
      64: ifeq          71
      67: iconst_1
      68: goto          72
      71: iconst_0
      72: ireturn
      73: iconst_0
      74: ireturn

  protected float getShadowRadius(S);
    descriptor: (Lnet/minecraft/client/render/entity/state/LivingEntityRenderState;)F
    Code:
       0: aload_0
       1: aload_1
       2: invokespecial #548                // Method net/minecraft/client/render/entity/EntityRenderer.getShadowRadius:(Lnet/minecraft/client/render/entity/state/EntityRenderState;)F
       5: aload_1
       6: getfield      #178                // Field net/minecraft/client/render/entity/state/LivingEntityRenderState.baseScale:F
       9: fmul
      10: freturn

  public void updateRenderState(T, S, float);
    descriptor: (Lnet/minecraft/entity/LivingEntity;Lnet/minecraft/client/render/entity/state/LivingEntityRenderState;F)V
    Code:
       0: aload_0
       1: aload_1
       2: aload_2
       3: fload_3
       4: invokespecial #554                // Method net/minecraft/client/render/entity/EntityRenderer.updateRenderState:(Lnet/minecraft/entity/Entity;Lnet/minecraft/client/render/entity/state/EntityRenderState;F)V
       7: fload_3
       8: aload_1
       9: getfield      #557                // Field net/minecraft/entity/LivingEntity.prevHeadYaw:F
      12: aload_1
      13: getfield      #560                // Field net/minecraft/entity/LivingEntity.headYaw:F
      16: invokestatic  #564                // Method net/minecraft/util/math/MathHelper.lerpAngleDegrees:(FFF)F
      19: fstore        4
      21: aload_2
      22: aload_1
      23: fload         4
      25: fload_3
      26: invokestatic  #568                // Method clampBodyYaw:(Lnet/minecraft/entity/LivingEntity;FF)F
      29: putfield      #184                // Field net/minecraft/client/render/entity/state/LivingEntityRenderState.bodyYaw:F
      32: aload_2
      33: fload         4
      35: aload_2
      36: getfield      #184                // Field net/minecraft/client/render/entity/state/LivingEntityRenderState.bodyYaw:F
      39: fsub
      40: invokestatic  #571                // Method net/minecraft/util/math/MathHelper.wrapDegrees:(F)F
      43: putfield      #266                // Field net/minecraft/client/render/entity/state/LivingEntityRenderState.yawDegrees:F
      46: aload_2
      47: aload_1
      48: fload_3
      49: invokevirtual #574                // Method net/minecraft/entity/LivingEntity.getLerpedPitch:(F)F
      52: putfield      #269                // Field net/minecraft/client/render/entity/state/LivingEntityRenderState.pitch:F
      55: aload_2
      56: aload_1
      57: invokevirtual #577                // Method net/minecraft/entity/LivingEntity.getCustomName:()Lnet/minecraft/text/Text;
      60: putfield      #581                // Field net/minecraft/client/render/entity/state/LivingEntityRenderState.customName:Lnet/minecraft/text/Text;
      63: aload_2
      64: aload_1
      65: invokestatic  #583                // Method shouldFlipUpsideDown:(Lnet/minecraft/entity/LivingEntity;)Z
      68: putfield      #427                // Field net/minecraft/client/render/entity/state/LivingEntityRenderState.flipUpsideDown:Z
      71: aload_2
      72: getfield      #427                // Field net/minecraft/client/render/entity/state/LivingEntityRenderState.flipUpsideDown:Z
      75: ifeq          100
      78: aload_2
      79: dup
      80: getfield      #269                // Field net/minecraft/client/render/entity/state/LivingEntityRenderState.pitch:F
      83: ldc           #189                // float -1.0f
      85: fmul
      86: putfield      #269                // Field net/minecraft/client/render/entity/state/LivingEntityRenderState.pitch:F
      89: aload_2
      90: dup
      91: getfield      #266                // Field net/minecraft/client/render/entity/state/LivingEntityRenderState.yawDegrees:F
      94: ldc           #189                // float -1.0f
      96: fmul
      97: putfield      #266                // Field net/minecraft/client/render/entity/state/LivingEntityRenderState.yawDegrees:F
     100: aload_1
     101: invokevirtual #586                // Method net/minecraft/entity/LivingEntity.hasVehicle:()Z
     104: ifne          141
     107: aload_1
     108: invokevirtual #589                // Method net/minecraft/entity/LivingEntity.isAlive:()Z
     111: ifeq          141
     114: aload_2
     115: aload_1
     116: getfield      #593                // Field net/minecraft/entity/LivingEntity.limbAnimator:Lnet/minecraft/entity/LimbAnimator;
     119: fload_3
     120: invokevirtual #598                // Method net/minecraft/entity/LimbAnimator.getPos:(F)F
     123: putfield      #601                // Field net/minecraft/client/render/entity/state/LivingEntityRenderState.limbFrequency:F
     126: aload_2
     127: aload_1
     128: getfield      #593                // Field net/minecraft/entity/LivingEntity.limbAnimator:Lnet/minecraft/entity/LimbAnimator;
     131: fload_3
     132: invokevirtual #604                // Method net/minecraft/entity/LimbAnimator.getSpeed:(F)F
     135: putfield      #607                // Field net/minecraft/client/render/entity/state/LivingEntityRenderState.limbAmplitudeMultiplier:F
     138: goto          151
     141: aload_2
     142: fconst_0
     143: putfield      #601                // Field net/minecraft/client/render/entity/state/LivingEntityRenderState.limbFrequency:F
     146: aload_2
     147: fconst_0
     148: putfield      #607                // Field net/minecraft/client/render/entity/state/LivingEntityRenderState.limbAmplitudeMultiplier:F
     151: aload_1
     152: invokevirtual #610                // Method net/minecraft/entity/LivingEntity.getVehicle:()Lnet/minecraft/entity/Entity;
     155: astore        6
     157: aload         6
     159: instanceof    #100                // class net/minecraft/entity/LivingEntity
     162: ifeq          188
     165: aload         6
     167: checkcast     #100                // class net/minecraft/entity/LivingEntity
     170: astore        5
     172: aload_2
     173: aload         5
     175: getfield      #593                // Field net/minecraft/entity/LivingEntity.limbAnimator:Lnet/minecraft/entity/LimbAnimator;
     178: fload_3
     179: invokevirtual #598                // Method net/minecraft/entity/LimbAnimator.getPos:(F)F
     182: putfield      #613                // Field net/minecraft/client/render/entity/state/LivingEntityRenderState.headItemAnimationProgress:F
     185: goto          196
     188: aload_2
     189: aload_2
     190: getfield      #601                // Field net/minecraft/client/render/entity/state/LivingEntityRenderState.limbFrequency:F
     193: putfield      #613                // Field net/minecraft/client/render/entity/state/LivingEntityRenderState.headItemAnimationProgress:F
     196: aload_2
     197: aload_1
     198: invokevirtual #616                // Method net/minecraft/entity/LivingEntity.getScale:()F
     201: putfield      #178                // Field net/minecraft/client/render/entity/state/LivingEntityRenderState.baseScale:F
     204: aload_2
     205: aload_1
     206: invokevirtual #619                // Method net/minecraft/entity/LivingEntity.getScaleFactor:()F
     209: putfield      #622                // Field net/minecraft/client/render/entity/state/LivingEntityRenderState.ageScale:F
     212: aload_2
     213: aload_1
     214: invokevirtual #626                // Method net/minecraft/entity/LivingEntity.getPose:()Lnet/minecraft/entity/EntityPose;
     217: putfield      #629                // Field net/minecraft/client/render/entity/state/LivingEntityRenderState.pose:Lnet/minecraft/entity/EntityPose;
     220: aload_2
     221: aload_1
     222: invokevirtual #633                // Method net/minecraft/entity/LivingEntity.getSleepingDirection:()Lnet/minecraft/util/math/Direction;
     225: putfield      #159                // Field net/minecraft/client/render/entity/state/LivingEntityRenderState.sleepingDirection:Lnet/minecraft/util/math/Direction;
     228: aload_2
     229: getfield      #159                // Field net/minecraft/client/render/entity/state/LivingEntityRenderState.sleepingDirection:Lnet/minecraft/util/math/Direction;
     232: ifnull        246
     235: aload_2
     236: aload_1
     237: getstatic     #636                // Field net/minecraft/entity/EntityPose.STANDING:Lnet/minecraft/entity/EntityPose;
     240: invokevirtual #640                // Method net/minecraft/entity/LivingEntity.getEyeHeight:(Lnet/minecraft/entity/EntityPose;)F
     243: putfield      #162                // Field net/minecraft/client/render/entity/state/LivingEntityRenderState.standingEyeHeight:F
     246: aload_2
     247: aload_1
     248: invokevirtual #643                // Method net/minecraft/entity/LivingEntity.isFrozen:()Z
     251: putfield      #360                // Field net/minecraft/client/render/entity/state/LivingEntityRenderState.shaking:Z
     254: aload_2
     255: aload_1
     256: invokevirtual #646                // Method net/minecraft/entity/LivingEntity.isBaby:()Z
     259: putfield      #649                // Field net/minecraft/client/render/entity/state/LivingEntityRenderState.baby:Z
     262: aload_2
     263: aload_1
     264: invokevirtual #652                // Method net/minecraft/entity/LivingEntity.isTouchingWater:()Z
     267: putfield      #655                // Field net/minecraft/client/render/entity/state/LivingEntityRenderState.touchingWater:Z
     270: aload_2
     271: aload_1
     272: invokevirtual #658                // Method net/minecraft/entity/LivingEntity.isUsingRiptide:()Z
     275: putfield      #417                // Field net/minecraft/client/render/entity/state/LivingEntityRenderState.usingRiptide:Z
     278: aload_2
     279: aload_1
     280: getfield      #661                // Field net/minecraft/entity/LivingEntity.hurtTime:I
     283: ifgt          293
     286: aload_1
     287: getfield      #663                // Field net/minecraft/entity/LivingEntity.deathTime:I
     290: ifle          297
     293: iconst_1
     294: goto          298
     297: iconst_0
     298: putfield      #334                // Field net/minecraft/client/render/entity/state/LivingEntityRenderState.hurt:Z
     301: aload_1
     302: getstatic     #98                 // Field net/minecraft/entity/EquipmentSlot.HEAD:Lnet/minecraft/entity/EquipmentSlot;
     305: invokevirtual #104                // Method net/minecraft/entity/LivingEntity.getEquippedStack:(Lnet/minecraft/entity/EquipmentSlot;)Lnet/minecraft/item/ItemStack;
     308: astore        5
     310: aload         5
     312: invokevirtual #667                // Method net/minecraft/item/ItemStack.getItem:()Lnet/minecraft/item/Item;
     315: astore        8
     317: aload         8
     319: instanceof    #669                // class net/minecraft/item/BlockItem
     322: ifeq          388
     325: aload         8
     327: checkcast     #669                // class net/minecraft/item/BlockItem
     330: astore        6
     332: aload         6
     334: invokevirtual #673                // Method net/minecraft/item/BlockItem.getBlock:()Lnet/minecraft/block/Block;
     337: astore        8
     339: aload         8
     341: instanceof    #675                // class net/minecraft/block/AbstractSkullBlock
     344: ifeq          388
     347: aload         8
     349: checkcast     #675                // class net/minecraft/block/AbstractSkullBlock
     352: astore        7
     354: aload_2
     355: aload         7
     357: invokevirtual #679                // Method net/minecraft/block/AbstractSkullBlock.getSkullType:()Lnet/minecraft/block/SkullBlock$SkullType;
     360: putfield      #683                // Field net/minecraft/client/render/entity/state/LivingEntityRenderState.wearingSkullType:Lnet/minecraft/block/SkullBlock$SkullType;
     363: aload_2
     364: aload         5
     366: getstatic     #689                // Field net/minecraft/component/DataComponentTypes.PROFILE:Lnet/minecraft/component/ComponentType;
     369: invokevirtual #693                // Method net/minecraft/item/ItemStack.get:(Lnet/minecraft/component/ComponentType;)Ljava/lang/Object;
     372: checkcast     #695                // class net/minecraft/component/type/ProfileComponent
     375: putfield      #699                // Field net/minecraft/client/render/entity/state/LivingEntityRenderState.wearingSkullProfile:Lnet/minecraft/component/type/ProfileComponent;
     378: aload_2
     379: getfield      #703                // Field net/minecraft/client/render/entity/state/LivingEntityRenderState.headItemRenderState:Lnet/minecraft/client/render/item/ItemRenderState;
     382: invokevirtual #708                // Method net/minecraft/client/render/item/ItemRenderState.clear:()V
     385: goto          437
     388: aload_2
     389: aconst_null
     390: putfield      #683                // Field net/minecraft/client/render/entity/state/LivingEntityRenderState.wearingSkullType:Lnet/minecraft/block/SkullBlock$SkullType;
     393: aload_2
     394: aconst_null
     395: putfield      #699                // Field net/minecraft/client/render/entity/state/LivingEntityRenderState.wearingSkullProfile:Lnet/minecraft/component/type/ProfileComponent;
     398: aload         5
     400: getstatic     #98                 // Field net/minecraft/entity/EquipmentSlot.HEAD:Lnet/minecraft/entity/EquipmentSlot;
     403: invokestatic  #714                // Method net/minecraft/client/render/entity/feature/ArmorFeatureRenderer.hasModel:(Lnet/minecraft/item/ItemStack;Lnet/minecraft/entity/EquipmentSlot;)Z
     406: ifne          430
     409: aload_0
     410: getfield      #62                 // Field itemModelResolver:Lnet/minecraft/client/item/ItemModelManager;
     413: aload_2
     414: getfield      #703                // Field net/minecraft/client/render/entity/state/LivingEntityRenderState.headItemRenderState:Lnet/minecraft/client/render/item/ItemRenderState;
     417: aload         5
     419: getstatic     #719                // Field net/minecraft/item/ModelTransformationMode.HEAD:Lnet/minecraft/item/ModelTransformationMode;
     422: iconst_0
     423: aload_1
     424: invokevirtual #725                // Method net/minecraft/client/item/ItemModelManager.updateForLivingEntity:(Lnet/minecraft/client/render/item/ItemRenderState;Lnet/minecraft/item/ItemStack;Lnet/minecraft/item/ModelTransformationMode;ZLnet/minecraft/entity/LivingEntity;)V
     427: goto          437
     430: aload_2
     431: getfield      #703                // Field net/minecraft/client/render/entity/state/LivingEntityRenderState.headItemRenderState:Lnet/minecraft/client/render/item/ItemRenderState;
     434: invokevirtual #708                // Method net/minecraft/client/render/item/ItemRenderState.clear:()V
     437: aload_2
     438: aload_1
     439: getfield      #663                // Field net/minecraft/entity/LivingEntity.deathTime:I
     442: ifle          455
     445: aload_1
     446: getfield      #663                // Field net/minecraft/entity/LivingEntity.deathTime:I
     449: i2f
     450: fload_3
     451: fadd
     452: goto          456
     455: fconst_0
     456: putfield      #401                // Field net/minecraft/client/render/entity/state/LivingEntityRenderState.deathTime:F
     459: invokestatic  #448                // Method net/minecraft/client/MinecraftClient.getInstance:()Lnet/minecraft/client/MinecraftClient;
     462: astore        6
     464: aload_2
     465: aload_2
     466: getfield      #344                // Field net/minecraft/client/render/entity/state/LivingEntityRenderState.invisible:Z
     469: ifeq          488
     472: aload_1
     473: aload         6
     475: getfield      #452                // Field net/minecraft/client/MinecraftClient.player:Lnet/minecraft/client/network/ClientPlayerEntity;
     478: invokevirtual #456                // Method net/minecraft/entity/LivingEntity.isInvisibleTo:(Lnet/minecraft/entity/player/PlayerEntity;)Z
     481: ifeq          488
     484: iconst_1
     485: goto          489
     488: iconst_0
     489: putfield      #207                // Field net/minecraft/client/render/entity/state/LivingEntityRenderState.invisibleToPlayer:Z
     492: aload_2
     493: aload         6
     495: aload_1
     496: invokevirtual #728                // Method net/minecraft/client/MinecraftClient.hasOutline:(Lnet/minecraft/entity/Entity;)Z
     499: putfield      #210                // Field net/minecraft/client/render/entity/state/LivingEntityRenderState.hasOutline:Z
     502: return

  private static float clampBodyYaw(net.minecraft.entity.LivingEntity, float, float);
    descriptor: (Lnet/minecraft/entity/LivingEntity;FF)F
    Code:
       0: aload_0
       1: invokevirtual #610                // Method net/minecraft/entity/LivingEntity.getVehicle:()Lnet/minecraft/entity/Entity;
       4: astore        4
       6: aload         4
       8: instanceof    #100                // class net/minecraft/entity/LivingEntity
      11: ifeq          89
      14: aload         4
      16: checkcast     #100                // class net/minecraft/entity/LivingEntity
      19: astore_3
      20: fload_2
      21: aload_3
      22: getfield      #740                // Field net/minecraft/entity/LivingEntity.prevBodyYaw:F
      25: aload_3
      26: getfield      #741                // Field net/minecraft/entity/LivingEntity.bodyYaw:F
      29: invokestatic  #564                // Method net/minecraft/util/math/MathHelper.lerpAngleDegrees:(FFF)F
      32: fstore        4
      34: ldc_w         #742                // float 85.0f
      37: fstore        5
      39: fload_1
      40: fload         4
      42: fsub
      43: invokestatic  #571                // Method net/minecraft/util/math/MathHelper.wrapDegrees:(F)F
      46: ldc_w         #743                // float -85.0f
      49: ldc_w         #742                // float 85.0f
      52: invokestatic  #746                // Method net/minecraft/util/math/MathHelper.clamp:(FFF)F
      55: fstore        6
      57: fload_1
      58: fload         6
      60: fsub
      61: fstore        4
      63: fload         6
      65: invokestatic  #749                // Method java/lang/Math.abs:(F)F
      68: ldc_w         #750                // float 50.0f
      71: fcmpl
      72: ifle          86
      75: fload         4
      77: fload         6
      79: ldc_w         #751                // float 0.2f
      82: fmul
      83: fadd
      84: fstore        4
      86: fload         4
      88: freturn
      89: fload_2
      90: aload_0
      91: getfield      #740                // Field net/minecraft/entity/LivingEntity.prevBodyYaw:F
      94: aload_0
      95: getfield      #741                // Field net/minecraft/entity/LivingEntity.bodyYaw:F
      98: invokestatic  #564                // Method net/minecraft/util/math/MathHelper.lerpAngleDegrees:(FFF)F
     101: freturn

  public void updateRenderState(net.minecraft.entity.Entity, net.minecraft.client.render.entity.state.EntityRenderState, float);
    descriptor: (Lnet/minecraft/entity/Entity;Lnet/minecraft/client/render/entity/state/EntityRenderState;F)V
    Code:
       0: aload_0
       1: aload_1
       2: checkcast     #100                // class net/minecraft/entity/LivingEntity
       5: aload_2
       6: checkcast     #151                // class net/minecraft/client/render/entity/state/LivingEntityRenderState
       9: fload_3
      10: invokevirtual #754                // Method updateRenderState:(Lnet/minecraft/entity/LivingEntity;Lnet/minecraft/client/render/entity/state/LivingEntityRenderState;F)V
      13: return

  protected float getShadowRadius(net.minecraft.client.render.entity.state.EntityRenderState);
    descriptor: (Lnet/minecraft/client/render/entity/state/EntityRenderState;)F
    Code:
       0: aload_0
       1: aload_1
       2: checkcast     #151                // class net/minecraft/client/render/entity/state/LivingEntityRenderState
       5: invokevirtual #758                // Method getShadowRadius:(Lnet/minecraft/client/render/entity/state/LivingEntityRenderState;)F
       8: freturn

  protected boolean hasLabel(net.minecraft.entity.Entity, double);
    descriptor: (Lnet/minecraft/entity/Entity;D)Z
    Code:
       0: aload_0
       1: aload_1
       2: checkcast     #100                // class net/minecraft/entity/LivingEntity
       5: dload_2
       6: invokevirtual #762                // Method hasLabel:(Lnet/minecraft/entity/LivingEntity;D)Z
       9: ireturn

  public void render(net.minecraft.client.render.entity.state.EntityRenderState, net.minecraft.client.util.math.MatrixStack, net.minecraft.client.render.VertexConsumerProvider, int);
    descriptor: (Lnet/minecraft/client/render/entity/state/EntityRenderState;Lnet/minecraft/client/util/math/MatrixStack;Lnet/minecraft/client/render/VertexConsumerProvider;I)V
    Code:
       0: aload_0
       1: aload_1
       2: checkcast     #151                // class net/minecraft/client/render/entity/state/LivingEntityRenderState
       5: aload_2
       6: aload_3
       7: iload         4
       9: invokevirtual #766                // Method render:(Lnet/minecraft/client/render/entity/state/LivingEntityRenderState;Lnet/minecraft/client/util/math/MatrixStack;Lnet/minecraft/client/render/VertexConsumerProvider;I)V
      12: return

  protected net.minecraft.util.math.Box getBoundingBox(net.minecraft.entity.Entity);
    descriptor: (Lnet/minecraft/entity/Entity;)Lnet/minecraft/util/math/Box;
    Code:
       0: aload_0
       1: aload_1
       2: checkcast     #100                // class net/minecraft/entity/LivingEntity
       5: invokevirtual #768                // Method getBoundingBox:(Lnet/minecraft/entity/LivingEntity;)Lnet/minecraft/util/math/Box;
       8: areturn
}
